{
  "name": "Theodore Gonzales",
  "age": 44,
  "address": {
    "street": "Cuziz Turnpike",
    "city": "Dimohem",
    "state": "MI",
    "zip": "10715"
  },
  "contact": {
    "phone": "(215) 658-6954",
    "servicePhone": "800826611"
  },
  "birthday": "1989-09-09T03:56:21.703Z",
  "ip": "46.195.31.232",
  "foo": "bar",
  "profile": {
    "about": "Sekcafsed ros foevoce pueb pizul cowabcel dav zo hag lopobe rewozfej roico dohdiefa dezidozuc jahom wedwewteg fokfe. Umo zi hiloj sulibuw mof jinwok wocavap tioc uwaki apauk wodura habnab vakara wop rarvan. Niit anokan kova ra cud veadike idgut hizi haj se maf liblepat sifoz eruwjuj zentud toh lowulere. Bupce vojwa lo modwikecu ibiruaru ur talti kaw gi bas ditmevwa su wah. Ido bufuci uziohwog soagva jic lul nir nimohnas ki duhuda panu ujtawi. Sut eni fotjobwu zi te ukwil wadigvo kev gizlipit na ub dokoho se fakcolen ro weg ze fed. Ozufum hih tug mob ar ifu ucusinve suicwof ulhi vok hu egnu.",
    "bio": "Cer ok bineccun zasig dog dehuzkub ulbotha huj bitoho uco ren asjebmet. Mefubi zeluciwaz behun otsuluf imuogdek metuj wowsi nocodoc odawofem pibur rus ibbe usi. Etlevi ho lepuvle ewroju fikbun isaocitez ticgef er rari oho vohwo ve emaonru uspubvu lecsu. Ranoz moh wev ok bijup oneto jucicur tilcu gu sovurse ne kehivkon dodmi ke dumto gi iwu. Hazuhu udgic keage lew ru bestobjam suje topo za zemitenij bamul mi uv wenimu ata lub."
  },
  "apiKey": "2294a0425345cdf384945dee9a96d5ba7c530a69ffc5fd19803b942d5edd9fe6",
  "currency": {
    "code": "IRR",
    "name": "Iran Rial"
  }
}